odoo9_addon_autovacuum_mail_message-9.0.1.0.0.99.dev1-py2.7-nspkg.pth
odoo9_addon_autovacuum_mail_message-9.0.1.0.0.99.dev1.dist-info/METADATA
odoo9_addon_autovacuum_mail_message-9.0.1.0.0.99.dev1.dist-info/RECORD
odoo9_addon_autovacuum_mail_message-9.0.1.0.0.99.dev1.dist-info/WHEEL
odoo9_addon_autovacuum_mail_message-9.0.1.0.0.99.dev1.dist-info/namespace_packages.txt
odoo9_addon_autovacuum_mail_message-9.0.1.0.0.99.dev1.dist-info/top_level.txt
odoo_addons/autovacuum_mail_message/README.rst
odoo_addons/autovacuum_mail_message/__init__.py
odoo_addons/autovacuum_mail_message/__openerp__.py
odoo_addons/autovacuum_mail_message/data/data.xml
odoo_addons/autovacuum_mail_message/i18n/autovacuum_mail_message.pot
odoo_addons/autovacuum_mail_message/i18n/fr.po
odoo_addons/autovacuum_mail_message/models/__init__.py
odoo_addons/autovacuum_mail_message/models/mail_message.py
odoo_addons/autovacuum_mail_message/models/message_vacuum_rule.py
odoo_addons/autovacuum_mail_message/security/ir.model.access.csv
odoo_addons/autovacuum_mail_message/static/description/icon.png
odoo_addons/autovacuum_mail_message/tests/__init__.py
odoo_addons/autovacuum_mail_message/tests/test_message_vacuum_rule.py
odoo_addons/autovacuum_mail_message/views/message_rule_vacuum.xml
